noe/__about__.py
noe/__init__.py
noe-0.0.1.dist-info/METADATA
noe-0.0.1.dist-info/WHEEL
noe-0.0.1.dist-info/licenses/LICENSE.txt
noe-0.0.1.dist-info/RECORD
