Metadata-Version: 2.4
Name: noe
Version: 0.0.1
Summary: A modern EON server component
Project-URL: Documentation, https://github.com/Rohit Goswami/noe#readme
Project-URL: Issues, https://github.com/Rohit Goswami/noe/issues
Project-URL: Source, https://github.com/Rohit Goswami/noe
Author-email: Rohit Goswami <rog32@hi.is>
License-Expression: MIT
License-File: LICENSE.txt
Classifier: Development Status :: 4 - Beta
Classifier: Programming Language :: Python
Classifier: Programming Language :: Python :: 3.8
Classifier: Programming Language :: Python :: 3.9
Classifier: Programming Language :: Python :: 3.10
Classifier: Programming Language :: Python :: 3.11
Classifier: Programming Language :: Python :: 3.12
Classifier: Programming Language :: Python :: Implementation :: CPython
Classifier: Programming Language :: Python :: Implementation :: PyPy
Requires-Python: >=3.8
